{
  "type": [
    "h-entry"
  ],
  "properties": {
    "author": [
      {
        "type": [
          "h-card"
        ],
        "properties": {
          "url": [
            "/profile/cleverdevil",
            "/profile/cleverdevil"
          ],
          "photo": [
            "/file/e37c3982acf4f0a8421d085b9971cd71/thumb.jpg"
          ],
          "name": [
            "Jonathan LaCour"
          ]
        },
        "value": "Jonathan LaCour"
      }
    ],
    "name": [
      "That reminds me: we need more talent. Yesterday. If you\u2019re an engineer looking to dive in deep with AWS across a broad set of problems and customers, let me know! Diversity is key. Bring it!"
    ],
    "content": [
      {
        "html": "That reminds me: we need more talent. Yesterday. If you\u2019re an engineer looking to dive in deep with AWS across a broad set of problems and customers, let me know! Diversity is key. Bring it!",
        "value": "That reminds me: we need more talent. Yesterday. If you\u2019re an engineer looking to dive in deep with AWS across a broad set of problems and customers, let me know! Diversity is key. Bring it!"
      }
    ],
    "url": [
      "/2018/that-reminds-me-we-need-more-talent-yesterday-if-youre"
    ],
    "published": [
      "2018-01-18T05:14:45+0000"
    ],
    "syndication": [
      "https://twitter.com/cleverdevil/status/953858175240998912"
    ],
    "post-kind": [
      "Status"
    ],
    "post-id": [
      "d05f54fe71bc74ff6551d31d5b5ac9fd"
    ],
    "like": [
      {
        "type": [
          "h-cite"
        ],
        "properties": {
          "url": [
            "https://twitter.com/cleverdevil/status/953858175240998912?known_from=https%3A%2F%2Fbrid-gy.appspot.com%2Flike%2Ftwitter%2Fcleverdevil%2F953858175240998912%2F15699553"
          ],
          "published": [
            "2018-01-18T05:49:49+00:00"
          ],
          "author": [
            {
              "type": [
                "h-card"
              ],
              "properties": {
                "name": [
                  "Jeff Campbell"
                ],
                "url": [
                  "https://twitter.com/Darchmare"
                ],
                "photo": [
                  "https://cleverdevil.io/service/web/imageproxy/aHR0cHM6Ly9wYnMudHdpbWcuY29tL3Byb2ZpbGVfaW1hZ2VzLzkyNTY0OTI1MjI4MTI4NjY2Mi9RdVhjQXJjQy5qcGc,/300/square"
                ]
              },
              "value": "https://cleverdevil.io/service/web/imageproxy/aHR0cHM6Ly9wYnMudHdpbWcuY29tL3Byb2ZpbGVfaW1hZ2VzLzkyNTY0OTI1MjI4MTI4NjY2Mi9RdVhjQXJjQy5qcGc,/300/square Jeff Campbell"
            }
          ]
        },
        "value": "Jeff Campbell"
      },
      {
        "type": [
          "h-cite"
        ],
        "properties": {
          "url": [
            "https://twitter.com/cleverdevil/status/953858175240998912?known_from=https%3A%2F%2Fbrid-gy.appspot.com%2Flike%2Ftwitter%2Fcleverdevil%2F953858175240998912%2F15847700"
          ],
          "published": [
            "2018-01-18T05:49:51+00:00"
          ],
          "author": [
            {
              "type": [
                "h-card"
              ],
              "properties": {
                "name": [
                  "\u018a\u024d\u02cc \u20a5\u25b2\u2020\u2020 (Not a licensed physician)"
                ],
                "url": [
                  "https://twitter.com/mattfelten"
                ],
                "photo": [
                  "https://cleverdevil.io/service/web/imageproxy/aHR0cHM6Ly9wYnMudHdpbWcuY29tL3Byb2ZpbGVfaW1hZ2VzLzc4MzQ4ODQ1NTE0OTkxNjE2MC9GM0NZX04yei5qcGc,/300/square"
                ]
              },
              "value": "https://cleverdevil.io/service/web/imageproxy/aHR0cHM6Ly9wYnMudHdpbWcuY29tL3Byb2ZpbGVfaW1hZ2VzLzc4MzQ4ODQ1NTE0OTkxNjE2MC9GM0NZX04yei5qcGc,/300/square \u018a\u024d\u02cc \u20a5\u25b2\u2020\u2020 (Not a licensed physician)"
            }
          ]
        },
        "value": "\u018a\u024d\u02cc \u20a5\u25b2\u2020\u2020 (Not a licensed physician)"
      },
      {
        "type": [
          "h-cite"
        ],
        "properties": {
          "url": [
            "https://twitter.com/cleverdevil/status/953858175240998912?known_from=https%3A%2F%2Fbrid-gy.appspot.com%2Flike%2Ftwitter%2Fcleverdevil%2F953858175240998912%2F274905126"
          ],
          "published": [
            "2018-01-18T07:19:28+00:00"
          ],
          "author": [
            {
              "type": [
                "h-card"
              ],
              "properties": {
                "name": [
                  "Sam"
                ],
                "url": [
                  "https://twitter.com/ssjbeeno"
                ],
                "photo": [
                  "https://cleverdevil.io/service/web/imageproxy/aHR0cHM6Ly9wYnMudHdpbWcuY29tL3Byb2ZpbGVfaW1hZ2VzLzkwOTMwNjcyNzU5MzQ3MjAwMS9TcVdBaGZsSi5qcGc,/300/square"
                ]
              },
              "value": "https://cleverdevil.io/service/web/imageproxy/aHR0cHM6Ly9wYnMudHdpbWcuY29tL3Byb2ZpbGVfaW1hZ2VzLzkwOTMwNjcyNzU5MzQ3MjAwMS9TcVdBaGZsSi5qcGc,/300/square Sam"
            }
          ]
        },
        "value": "Sam"
      },
      {
        "type": [
          "h-cite"
        ],
        "properties": {
          "url": [
            "https://twitter.com/cleverdevil/status/953858175240998912?known_from=https%3A%2F%2Fbrid-gy.appspot.com%2Flike%2Ftwitter%2Fcleverdevil%2F953858175240998912%2F744427567"
          ],
          "published": [
            "2018-01-18T08:49:13+00:00"
          ],
          "author": [
            {
              "type": [
                "h-card"
              ],
              "properties": {
                "name": [
                  "Ben Duncan"
                ],
                "url": [
                  "https://twitter.com/ben_colo"
                ],
                "photo": [
                  "https://cleverdevil.io/service/web/imageproxy/aHR0cHM6Ly9wYnMudHdpbWcuY29tL3Byb2ZpbGVfaW1hZ2VzLzczNTUzODExMDQ5OTQzMDQwMC9XSUFROUt1UC5qcGc,/300/square"
                ]
              },
              "value": "https://cleverdevil.io/service/web/imageproxy/aHR0cHM6Ly9wYnMudHdpbWcuY29tL3Byb2ZpbGVfaW1hZ2VzLzczNTUzODExMDQ5OTQzMDQwMC9XSUFROUt1UC5qcGc,/300/square Ben Duncan"
            }
          ]
        },
        "value": "Ben Duncan"
      },
      {
        "type": [
          "h-cite"
        ],
        "properties": {
          "url": [
            "https://twitter.com/cleverdevil/status/953858175240998912?known_from=https%3A%2F%2Fbrid-gy.appspot.com%2Flike%2Ftwitter%2Fcleverdevil%2F953858175240998912%2F53491074"
          ],
          "published": [
            "2018-01-19T03:24:10+00:00"
          ],
          "author": [
            {
              "type": [
                "h-card"
              ],
              "properties": {
                "name": [
                  "Justin Ryan"
                ],
                "url": [
                  "https://twitter.com/JustinRyanBear"
                ],
                "photo": [
                  "https://cleverdevil.io/service/web/imageproxy/aHR0cHM6Ly9wYnMudHdpbWcuY29tL3Byb2ZpbGVfaW1hZ2VzLzkzNzEzMDIwNzgxMDU0MzYxNy9WRTRSb2tUbi5qcGc,/300/square"
                ]
              },
              "value": "https://cleverdevil.io/service/web/imageproxy/aHR0cHM6Ly9wYnMudHdpbWcuY29tL3Byb2ZpbGVfaW1hZ2VzLzkzNzEzMDIwNzgxMDU0MzYxNy9WRTRSb2tUbi5qcGc,/300/square Justin Ryan"
            }
          ]
        },
        "value": "Justin Ryan"
      }
    ]
  }
}