{
  "type": [
    "h-entry"
  ],
  "properties": {
    "author": [
      {
        "type": [
          "h-card"
        ],
        "properties": {
          "url": [
            "/profile/cleverdevil",
            "/profile/cleverdevil"
          ],
          "photo": [
            "/file/e37c3982acf4f0a8421d085b9971cd71/thumb.jpg"
          ],
          "name": [
            "Jonathan LaCour"
          ]
        },
        "value": "Jonathan LaCour"
      },
      {
        "type": [
          "h-card"
        ],
        "properties": {
          "photo": [
            "/file/e37c3982acf4f0a8421d085b9971cd71/thumb.jpg"
          ],
          "logo": [
            "/file/e37c3982acf4f0a8421d085b9971cd71/thumb.jpg"
          ],
          "name": [
            "Jonathan LaCour"
          ],
          "url": [
            "/profile/cleverdevil",
            "/profile/cleverdevil"
          ]
        },
        "value": "Jonathan LaCour"
      }
    ],
    "name": [
      "Watched Taskmaster 14x08 \"The One That Bats Do\""
    ],
    "item": [
      {
        "type": [
          "h-product"
        ],
        "properties": {
          "photo": [
            "https://cleverdevil.io/file/38bfa3eb93750ae9dda1e5eb6a1f1125/thumb.jpg"
          ],
          "name": [
            "Taskmaster 14x08 \"The One That Bats Do\""
          ],
          "url": [
            "https://trakt.tv/episodes/6708688"
          ]
        },
        "value": "Taskmaster 14x08 \"The One That Bats Do\""
      }
    ],
    "content": [
      {
        "html": "<p>Fern Brady and Munya Chawawa are yet to claim a win. Can a rare tailless tiger bring them luck? Meanwhile, Dara \u00d3 Briain gets frustrated, and Sarah Millican does something clever.</p>\n\n                                <p style=\"font-style: italic; text-align: right;\">Watched on Trakt</p>",
        "value": "Fern Brady and Munya Chawawa are yet to claim a win. Can a rare tailless tiger bring them luck? Meanwhile, Dara \u00d3 Briain gets frustrated, and Sarah Millican does something clever.\nWatched on Trakt"
      }
    ],
    "url": [
      "/2022/taskmaster-14x08-the-one-that-bats-do-1"
    ],
    "published": [
      "2022-12-29T02:04:35+0000"
    ],
    "post-kind": [
      "Watching"
    ],
    "post-id": [
      "df99c64411b036946d85233fbf2f0118"
    ],
    "location-metadata": {
      "timestamp": "2022-12-29T01:54:03Z",
      "year": 2022,
      "month": 12,
      "day": 29,
      "hour": 1,
      "minute": 54,
      "x": -118.37046236570359,
      "y": 33.8152668133675,
      "altitude": 56,
      "motion": [],
      "speed": 0,
      "battery_state": "unplugged",
      "battery_level": 0.8399999737739563,
      "wifi": "LaCour"
    }
  }
}