{
  "type": [
    "h-entry"
  ],
  "properties": {
    "author": [
      {
        "type": [
          "h-card"
        ],
        "properties": {
          "url": [
            "/profile/cleverdevil",
            "/profile/cleverdevil"
          ],
          "photo": [
            "/file/e37c3982acf4f0a8421d085b9971cd71/thumb.jpg"
          ],
          "name": [
            "Jonathan LaCour"
          ]
        },
        "value": "Jonathan LaCour"
      },
      {
        "type": [
          "h-card"
        ],
        "properties": {
          "photo": [
            "/file/e37c3982acf4f0a8421d085b9971cd71/thumb.jpg"
          ],
          "logo": [
            "/file/e37c3982acf4f0a8421d085b9971cd71/thumb.jpg"
          ],
          "name": [
            "Jonathan LaCour"
          ],
          "url": [
            "/profile/cleverdevil",
            "/profile/cleverdevil"
          ]
        },
        "value": "Jonathan LaCour"
      }
    ],
    "name": [
      "Watched The Amazing Race, Season 29 - Riding a Bike is Like Riding a Bike"
    ],
    "item": [
      {
        "type": [
          "h-product"
        ],
        "properties": {
          "photo": [
            "https://cleverdevil.io/file/76bdf8b7973a482e944b862be1d8319d/thumb.jpg"
          ],
          "name": [
            "The Amazing Race, Season 29 - Riding a Bike is Like Riding a Bike"
          ],
          "url": [
            "http://thetvdb.com/?tab=series&id=77666"
          ]
        },
        "value": "The Amazing Race, Season 29 - Riding a Bike is Like Riding a Bike"
      }
    ],
    "content": [
      {
        "html": "<p>Teams battle the scorching heat while transporting shrimp baskets for one mile to a local fisherman, and one Racer approaches their breaking point during the exhausting Roadblock.</p>\n\n                                <p style=\"font-style: italic; text-align: right;\">Watched on Bedroom</p>",
        "value": "Teams battle the scorching heat while transporting shrimp baskets for one mile to a local fisherman, and one Racer approaches their breaking point during the exhausting Roadblock.\nWatched on Bedroom"
      }
    ],
    "url": [
      "/2017/the-amazing-race-season-29---riding-a-bike-is"
    ],
    "published": [
      "2017-05-22T03:01:15+0000"
    ],
    "post-kind": [
      "Watching"
    ],
    "post-id": [
      "25a145fe2a4bff66bce929ec694fd860"
    ]
  }
}