{
  "type": [
    "h-entry"
  ],
  "properties": {
    "author": [
      {
        "type": [
          "h-card"
        ],
        "properties": {
          "url": [
            "/profile/cleverdevil",
            "/profile/cleverdevil"
          ],
          "photo": [
            "/file/e37c3982acf4f0a8421d085b9971cd71/thumb.jpg"
          ],
          "name": [
            "Jonathan LaCour"
          ]
        },
        "value": "Jonathan LaCour"
      }
    ],
    "name": [
      "Checked into Rocketship Park"
    ],
    "location": [
      {
        "type": [
          "h-card"
        ],
        "properties": {
          "name": [
            "Rocketship Park"
          ],
          "latitude": [
            "33.808307897273"
          ],
          "longitude": [
            "-118.37045152672"
          ]
        },
        "value": "Rocketship Park"
      }
    ],
    "checkin": [
      {
        "type": [
          "h-card"
        ],
        "properties": {
          "name": [
            "Rocketship Park"
          ],
          "latitude": [
            "33.808307897273"
          ],
          "longitude": [
            "-118.37045152672"
          ]
        },
        "value": ""
      }
    ],
    "content": [
      {
        "html": "<p>Playtime with the kids!</p>",
        "value": "Playtime with the kids!"
      }
    ],
    "url": [
      "/2017/checked-into-rocketship-park"
    ],
    "published": [
      "2017-04-01T18:25:52+0000"
    ],
    "comment": [
      {
        "type": [
          "h-cite"
        ],
        "properties": {
          "summary": [
            "First of your friends to check into Riviera!"
          ],
          "content": [
            {
              "html": "<p>First of your friends to check into Riviera!</p>",
              "value": "First of your friends to check into Riviera!"
            }
          ],
          "author": [
            {
              "type": [
                "h-card"
              ],
              "properties": {
                "photo": [
                  "https://cleverdevil.io/file/05e7c69abf3bcc43ccd381c911b2d5a0"
                ],
                "name": [
                  "Swarm"
                ],
                "url": [
                  "https://swarmapp.com/"
                ]
              },
              "value": "Swarm"
            }
          ],
          "url": [
            "https://ownyourswarm.p3k.io/checkin/58dff0adc9602718468e7737/36736762cced7139adae4122e8d4ee1e"
          ]
        },
        "value": "https://ownyourswarm.p3k.io/checkin/58dff0adc9602718468e7737/36736762cced7139adae4122e8d4ee1e"
      },
      {
        "type": [
          "h-cite"
        ],
        "properties": {
          "summary": [
            "First check-in in Riviera."
          ],
          "content": [
            {
              "html": "<p>First check-in in Riviera.</p>",
              "value": "First check-in in Riviera."
            }
          ],
          "author": [
            {
              "type": [
                "h-card"
              ],
              "properties": {
                "photo": [
                  "https://cleverdevil.io/file/921567ebbce8b90cd8745a63eccd785a"
                ],
                "name": [
                  "Swarm"
                ],
                "url": [
                  "https://swarmapp.com/"
                ]
              },
              "value": "Swarm"
            }
          ],
          "url": [
            "https://ownyourswarm.p3k.io/checkin/58dff0adc9602718468e7737/ffbff012ad75508e7486cf4221105692"
          ]
        },
        "value": "https://ownyourswarm.p3k.io/checkin/58dff0adc9602718468e7737/ffbff012ad75508e7486cf4221105692"
      },
      {
        "type": [
          "h-cite"
        ],
        "properties": {
          "summary": [
            "Nice photo. You're gonna want some 3x5 glossy doubles."
          ],
          "content": [
            {
              "html": "<p>Nice photo. You're gonna want some 3x5 glossy doubles.</p>",
              "value": "Nice photo. You're gonna want some 3x5 glossy doubles."
            }
          ],
          "author": [
            {
              "type": [
                "h-card"
              ],
              "properties": {
                "photo": [
                  "https://cleverdevil.io/file/921567ebbce8b90cd8745a63eccd785a"
                ],
                "name": [
                  "Swarm"
                ],
                "url": [
                  "https://swarmapp.com/"
                ]
              },
              "value": "Swarm"
            }
          ],
          "url": [
            "https://ownyourswarm.p3k.io/checkin/58dff0adc9602718468e7737/82871940353a5f97608d81fd0e67a930"
          ]
        },
        "value": "https://ownyourswarm.p3k.io/checkin/58dff0adc9602718468e7737/82871940353a5f97608d81fd0e67a930"
      },
      {
        "type": [
          "h-cite"
        ],
        "properties": {
          "summary": [
            "First of your friends to check in here."
          ],
          "content": [
            {
              "html": "<p>First of your friends to check in here.</p>",
              "value": "First of your friends to check in here."
            }
          ],
          "author": [
            {
              "type": [
                "h-card"
              ],
              "properties": {
                "photo": [
                  "https://cleverdevil.io/file/505912cd3a1721392cf53972b9881063"
                ],
                "name": [
                  "Swarm"
                ],
                "url": [
                  "https://swarmapp.com/"
                ]
              },
              "value": "Swarm"
            }
          ],
          "url": [
            "https://ownyourswarm.p3k.io/checkin/58dff0adc9602718468e7737/901d2062fe377d8f54b57d96cafc0d5b"
          ]
        },
        "value": "https://ownyourswarm.p3k.io/checkin/58dff0adc9602718468e7737/901d2062fe377d8f54b57d96cafc0d5b"
      },
      {
        "type": [
          "h-cite"
        ],
        "properties": {
          "summary": [
            "Your first Scenic Lookout."
          ],
          "content": [
            {
              "html": "<p>Your first Scenic Lookout.</p>",
              "value": "Your first Scenic Lookout."
            }
          ],
          "author": [
            {
              "type": [
                "h-card"
              ],
              "properties": {
                "photo": [
                  "https://cleverdevil.io/file/4401b5cdf0b59fe6802ff4a191316f23"
                ],
                "name": [
                  "Swarm"
                ],
                "url": [
                  "https://swarmapp.com/"
                ]
              },
              "value": "Swarm"
            }
          ],
          "url": [
            "https://ownyourswarm.p3k.io/checkin/58dff0adc9602718468e7737/ae1ec1020f59e322889908284d117920"
          ]
        },
        "value": "https://ownyourswarm.p3k.io/checkin/58dff0adc9602718468e7737/ae1ec1020f59e322889908284d117920"
      },
      {
        "type": [
          "h-cite"
        ],
        "properties": {
          "summary": [
            "Your first check-in at Rocketship Park!"
          ],
          "content": [
            {
              "html": "<p>Your first check-in at Rocketship Park!</p>",
              "value": "Your first check-in at Rocketship Park!"
            }
          ],
          "author": [
            {
              "type": [
                "h-card"
              ],
              "properties": {
                "photo": [
                  "https://cleverdevil.io/file/f5f89356f459a9e7b43c3699d0fc7912"
                ],
                "name": [
                  "Swarm"
                ],
                "url": [
                  "https://swarmapp.com/"
                ]
              },
              "value": "Swarm"
            }
          ],
          "url": [
            "https://ownyourswarm.p3k.io/checkin/58dff0adc9602718468e7737/eb84b537c662934449016595ad60e2fe"
          ]
        },
        "value": "https://ownyourswarm.p3k.io/checkin/58dff0adc9602718468e7737/eb84b537c662934449016595ad60e2fe"
      }
    ],
    "syndication": [
      "https://www.swarmapp.com/user/62573/checkin/58dff0adc9602718468e7737"
    ],
    "post-kind": [
      "Checkin"
    ],
    "post-id": [
      "4592cff944d039737616a20a2c476d47"
    ]
  }
}