{
  "type": [
    "h-entry"
  ],
  "properties": {
    "author": [
      {
        "type": [
          "h-card"
        ],
        "properties": {
          "url": [
            "/profile/cleverdevil",
            "/profile/cleverdevil"
          ],
          "photo": [
            "/file/e37c3982acf4f0a8421d085b9971cd71/thumb.jpg"
          ],
          "name": [
            "Jonathan LaCour"
          ]
        },
        "value": "Jonathan LaCour"
      }
    ],
    "name": [
      "Current status. #BestNeighborhood"
    ],
    "content": [
      {
        "html": "<div class=\"photo-view\">\n                <a data-footer=\"\" data-gallery=\"Current status. #BestNeighborhood\" data-original-img=\"https://cleverdevil.io/file/d03dee12b8874b35e884fc7007bf924e/cleverdevil.2014-10-5+14h48m27s0.tyVXJntRQG.jpg\" data-title=\"Current status. #BestNeighborhood\" href=\"https://cleverdevil.io/file/d03dee12b8874b35e884fc7007bf924e/cleverdevil.2014-10-5+14h48m27s0.tyVXJntRQG.jpg\"><img alt=\"Current status. #BestNeighborhood\" class=\"u-photo\" src=\"https://cleverdevil.io/file/d03dee12b8874b35e884fc7007bf924e/cleverdevil.2014-10-5+14h48m27s0.tyVXJntRQG.jpg\"/></a>\n            </div>",
        "value": "Current status. #BestNeighborhood"
      }
    ],
    "photo": [
      "https://cleverdevil.io/file/d03dee12b8874b35e884fc7007bf924e/cleverdevil.2014-10-5+14h48m27s0.tyVXJntRQG.jpg"
    ],
    "url": [
      "/2014/current-status-bestneighborhood"
    ],
    "published": [
      "2014-10-05T21:48:27+0000"
    ],
    "syndication": [
      "https://www.instagram.com/p/tyVXJntRQG/"
    ],
    "post-kind": [
      "Photo"
    ],
    "post-id": [
      "e8c041a68f790fe82b851266f873e069"
    ]
  }
}