{
  "type": [
    "h-entry"
  ],
  "properties": {
    "author": [
      {
        "type": [
          "h-card"
        ],
        "properties": {
          "url": [
            "/profile/cleverdevil",
            "/profile/cleverdevil"
          ],
          "photo": [
            "/file/e37c3982acf4f0a8421d085b9971cd71/thumb.jpg"
          ],
          "name": [
            "Jonathan LaCour"
          ]
        },
        "value": "Jonathan LaCour"
      },
      {
        "type": [
          "h-card"
        ],
        "properties": {
          "photo": [
            "/file/e37c3982acf4f0a8421d085b9971cd71/thumb.jpg"
          ],
          "logo": [
            "/file/e37c3982acf4f0a8421d085b9971cd71/thumb.jpg"
          ],
          "name": [
            "Jonathan LaCour"
          ],
          "url": [
            "/profile/cleverdevil",
            "/profile/cleverdevil"
          ]
        },
        "value": "Jonathan LaCour"
      }
    ],
    "name": [
      "Watched American Ninja Warrior 15x14 \"Las Vegas Finals 4\""
    ],
    "item": [
      {
        "type": [
          "h-product"
        ],
        "properties": {
          "photo": [
            "https://cleverdevil.io/file/47f7b2cc6d66ce3e9e9abbf3655d81b4/thumb.jpg"
          ],
          "name": [
            "American Ninja Warrior 15x14 \"Las Vegas Finals 4\""
          ],
          "url": [
            "https://trakt.tv/episodes/10847347"
          ]
        },
        "value": "American Ninja Warrior 15x14 \"Las Vegas Finals 4\""
      }
    ],
    "content": [
      {
        "html": "<p>The National Finals conclude in Las Vegas as the remaining ninjas compete in Stage 3 and 4 and a $1 million winner is crowned as the next American Ninja Warrior.</p>\n\n                                <p style=\"font-style: italic; text-align: right;\">Watched on Trakt</p>",
        "value": "The National Finals conclude in Las Vegas as the remaining ninjas compete in Stage 3 and 4 and a $1 million winner is crowned as the next American Ninja Warrior.\nWatched on Trakt"
      }
    ],
    "url": [
      "/2023/american-ninja-warrior-15x14-las-vegas-finals-4"
    ],
    "published": [
      "2023-09-14T03:00:03+0000"
    ],
    "post-kind": [
      "Watching"
    ],
    "post-id": [
      "b826d15b9a9f93d0fe5bb646effd375c"
    ],
    "location-metadata": {
      "timestamp": "2023-09-13T19:16:27Z",
      "year": 2023,
      "month": 9,
      "day": 13,
      "hour": 19,
      "minute": 16,
      "x": -109.73608899711532,
      "y": 22.992718384357755,
      "altitude": 36,
      "motion": [],
      "speed": 5,
      "battery_state": "unplugged",
      "battery_level": 0.4000000059604645,
      "wifi": ""
    }
  }
}