{
  "type": [
    "h-entry"
  ],
  "properties": {
    "author": [
      {
        "type": [
          "h-card"
        ],
        "properties": {
          "url": [
            "/profile/cleverdevil",
            "/profile/cleverdevil"
          ],
          "photo": [
            "/file/e37c3982acf4f0a8421d085b9971cd71/thumb.jpg"
          ],
          "name": [
            "Jonathan LaCour"
          ]
        },
        "value": "Jonathan LaCour"
      }
    ],
    "name": [
      "I\u2019m not even through the first episode of Silo, and I\u2019m absolutely over the moon. Adapting a great book, especially a great spec fic book, is damn near impossible. This is remarkable. Absolutely remarkable."
    ],
    "content": [
      {
        "html": "I\u2019m not even through the first episode of Silo, and I\u2019m absolutely over the moon. Adapting a great book, especially a great spec fic book, is damn near impossible. This is remarkable. Absolutely remarkable.",
        "value": "I\u2019m not even through the first episode of Silo, and I\u2019m absolutely over the moon. Adapting a great book, especially a great spec fic book, is damn near impossible. This is remarkable. Absolutely remarkable."
      }
    ],
    "url": [
      "/2023/im-not-even-through-the-first-episode"
    ],
    "published": [
      "2023-05-08T05:56:01+0000"
    ],
    "syndication": [
      "https://cleverdevil.club/@jonathan/110331519346805182"
    ],
    "post-kind": [
      "Status"
    ],
    "post-id": [
      "185890bf10cc77e20f4ae358ca3bcfee"
    ],
    "like": [
      {
        "type": [
          "h-cite"
        ],
        "properties": {
          "url": [
            "https://cleverdevil.club/@jonathan/110331519346805182#favorited-by-109368496481741909"
          ],
          "published": [
            "2023-05-08T10:22:15+00:00"
          ],
          "author": [
            {
              "type": [
                "h-card"
              ],
              "properties": {
                "name": [
                  "Jeff C. \ud83c\uddfa\ud83c\udde6"
                ],
                "url": [
                  "https://indieweb.social/@jeff"
                ],
                "photo": [
                  "https://cleverdevil.io/service/web/imageproxy/aHR0cHM6Ly9jbGV2ZXJkZXZpbC5jbHViL3N5c3RlbS9jYWNoZS9hY2NvdW50cy9hdmF0YXJzLzEwOS8zNjgvNDk2LzQ4MS83NDEvOTA5L29yaWdpbmFsL2I0MjVmMDEzODNlY2RkM2IuanBn/300/square"
                ]
              },
              "value": "https://cleverdevil.io/service/web/imageproxy/aHR0cHM6Ly9jbGV2ZXJkZXZpbC5jbHViL3N5c3RlbS9jYWNoZS9hY2NvdW50cy9hdmF0YXJzLzEwOS8zNjgvNDk2LzQ4MS83NDEvOTA5L29yaWdpbmFsL2I0MjVmMDEzODNlY2RkM2IuanBn/300/square Jeff C. \ud83c\uddfa\ud83c\udde6"
            }
          ]
        },
        "value": "Jeff C. \ud83c\uddfa\ud83c\udde6"
      },
      {
        "type": [
          "h-cite"
        ],
        "properties": {
          "url": [
            "https://cleverdevil.club/@jonathan/110331519346805182#favorited-by-109734746509292002"
          ],
          "published": [
            "2023-05-08T10:51:09+00:00"
          ],
          "author": [
            {
              "type": [
                "h-card"
              ],
              "properties": {
                "name": [
                  "Jon (TechNurseJon) :finsup:"
                ],
                "url": [
                  "https://finsup.social/@jon"
                ],
                "photo": [
                  "https://cleverdevil.io/service/web/imageproxy/aHR0cHM6Ly9jbGV2ZXJkZXZpbC5jbHViL3N5c3RlbS9jYWNoZS9hY2NvdW50cy9hdmF0YXJzLzEwOS83MzQvNzQ2LzUwOS8yOTIvMDAyL29yaWdpbmFsLzA1YzJjMzViZDhjZTVhMWYuanBn/300/square"
                ]
              },
              "value": "https://cleverdevil.io/service/web/imageproxy/aHR0cHM6Ly9jbGV2ZXJkZXZpbC5jbHViL3N5c3RlbS9jYWNoZS9hY2NvdW50cy9hdmF0YXJzLzEwOS83MzQvNzQ2LzUwOS8yOTIvMDAyL29yaWdpbmFsLzA1YzJjMzViZDhjZTVhMWYuanBn/300/square Jon (TechNurseJon) :finsup:"
            }
          ]
        },
        "value": "Jon (TechNurseJon) :finsup:"
      }
    ],
    "location-metadata": {
      "timestamp": "2023-05-02T03:34:09Z",
      "year": 2023,
      "month": 5,
      "day": 2,
      "hour": 3,
      "minute": 34,
      "x": -116.38021025937194,
      "y": 33.701708020729185,
      "altitude": 264,
      "motion": [],
      "speed": -1,
      "battery_state": "unplugged",
      "battery_level": 0.6899999976158142,
      "wifi": "DesertSun"
    }
  }
}