{
  "type": [
    "h-entry"
  ],
  "properties": {
    "author": [
      {
        "type": [
          "h-card"
        ],
        "properties": {
          "url": [
            "/profile/cleverdevil",
            "/profile/cleverdevil"
          ],
          "photo": [
            "/file/e37c3982acf4f0a8421d085b9971cd71/thumb.jpg"
          ],
          "name": [
            "Jonathan LaCour"
          ]
        },
        "value": "Jonathan LaCour"
      }
    ],
    "name": [
      "Pillow Fight. \u2013 The Everywhereist"
    ],
    "like-of": [
      "http://www.everywhereist.com/pillow-fight/"
    ],
    "url": [
      "/2018/pillow-fight-the-everywhereist"
    ],
    "published": [
      "2018-03-20T06:11:14+0000"
    ],
    "post-kind": [
      "Like"
    ],
    "post-id": [
      "65622f7e9c4083c20ba1872a77d92b26"
    ]
  }
}