{
  "type": [
    "h-entry"
  ],
  "properties": {
    "author": [
      {
        "type": [
          "h-card"
        ],
        "properties": {
          "url": [
            "/profile/cleverdevil",
            "/profile/cleverdevil"
          ],
          "photo": [
            "/file/e37c3982acf4f0a8421d085b9971cd71/thumb.jpg"
          ],
          "name": [
            "Jonathan LaCour"
          ]
        },
        "value": "Jonathan LaCour"
      },
      {
        "type": [
          "h-card"
        ],
        "properties": {
          "photo": [
            "/file/e37c3982acf4f0a8421d085b9971cd71/thumb.jpg"
          ],
          "logo": [
            "/file/e37c3982acf4f0a8421d085b9971cd71/thumb.jpg"
          ],
          "name": [
            "Jonathan LaCour"
          ],
          "url": [
            "/profile/cleverdevil",
            "/profile/cleverdevil"
          ]
        },
        "value": "Jonathan LaCour"
      }
    ],
    "name": [
      "Watched Gold Rush: White Water 5x13 \"The Motherload\""
    ],
    "item": [
      {
        "type": [
          "h-product"
        ],
        "properties": {
          "photo": [
            "https://cleverdevil.io/file/bc928b72253278dea81e9691a3bda1fb/thumb.jpg"
          ],
          "name": [
            "Gold Rush: White Water 5x13 \"The Motherload\""
          ],
          "url": [
            "https://trakt.tv/episodes/5933790"
          ]
        },
        "value": "Gold Rush: White Water 5x13 \"The Motherload\""
      }
    ],
    "content": [
      {
        "html": "<p>Dustin is within inches of bedrock gold at the Chute, but intense pressure causes one crewmember to crack. Kayla battles the mammoth dive site at House Rock, but attempts to keep the site safe backfire and a close call sets them back weeks.</p>\n\n                                <p style=\"font-style: italic; text-align: right;\">Watched on Trakt</p>",
        "value": "Dustin is within inches of bedrock gold at the Chute, but intense pressure causes one crewmember to crack. Kayla battles the mammoth dive site at House Rock, but attempts to keep the site safe backfire and a close call sets them back weeks.\nWatched on Trakt"
      }
    ],
    "url": [
      "/2022/gold-rush-white-water-5x13-the-motherload"
    ],
    "published": [
      "2022-02-27T06:00:03+0000"
    ],
    "post-kind": [
      "Watching"
    ],
    "post-id": [
      "a10e73bfefc2f9e1b645f0ac2acc7bac"
    ],
    "location-metadata": {
      "timestamp": "2022-02-27T05:55:46Z",
      "year": 2022,
      "month": 2,
      "day": 27,
      "hour": 5,
      "minute": 55,
      "x": -118.37031061090387,
      "y": 33.81540636008972,
      "altitude": 54,
      "motion": [],
      "speed": 0,
      "battery_state": "unplugged",
      "battery_level": 0.5699999928474426,
      "wifi": "LaCour"
    }
  }
}